puretable/__init__.py
puretable/table.py
puretable-0.0.2.dist-info/LICENSE
puretable-0.0.2.dist-info/METADATA
puretable-0.0.2.dist-info/WHEEL
puretable-0.0.2.dist-info/top_level.txt
puretable-0.0.2.dist-info/RECORD
